dataframe_to_pg/__init__.py
dataframe_to_pg/py.typed
dataframe_to_pg/writer.py
dataframe_to_pg-0.7.0.dist-info/licenses/LICENSE
dataframe_to_pg-0.7.0.dist-info/METADATA
dataframe_to_pg-0.7.0.dist-info/WHEEL
dataframe_to_pg-0.7.0.dist-info/top_level.txt
dataframe_to_pg-0.7.0.dist-info/RECORD
