Metadata-Version: 2.4
Name: dataframe-to-pg
Version: 0.7.0
Summary: DataFrame to PostgreSQL Writer
Author-email: Mark Moreno <mark@securehst.com>
License: MIT
Project-URL: Bug Tracker, https://github.com/markm-io/dataframe-to-pg/issues
Project-URL: Changelog, https://github.com/markm-io/dataframe-to-pg/blob/main/CHANGELOG.md
Project-URL: documentation, https://dataframe-to-pg.readthedocs.io
Project-URL: repository, https://github.com/markm-io/dataframe-to-pg
Classifier: Development Status :: 2 - Pre-Alpha
Classifier: Intended Audience :: Developers
Classifier: Natural Language :: English
Classifier: Operating System :: OS Independent
Classifier: Programming Language :: Python :: 3.9
Classifier: Programming Language :: Python :: 3.10
Classifier: Programming Language :: Python :: 3.11
Classifier: Programming Language :: Python :: 3.12
Classifier: Programming Language :: Python :: 3.13
Classifier: Topic :: Software Development :: Libraries
Requires-Python: >=3.9
License-File: LICENSE
Requires-Dist: pandas>=2.2.3
Requires-Dist: polars>=1.21.0
Requires-Dist: psycopg2-binary>=2.9.10
Requires-Dist: pyjanitor>=0.30.0
Requires-Dist: sqlalchemy>=2.0.37
Requires-Dist: tqdm>=4.67.1
Dynamic: license-file
